<?xml version="1.0" encoding="UTF-8"?>
<r>
   <e>
      <lg>
         <l pos="pcle">nov</l>
      </lg>
      <mg>
         <tg>
            <t pos="pcle">visst</t>
         </tg>
      </mg>
   </e>
   <e>
      <lg>
         <l pos="pcle">amma</l>
      </lg>
      <mg>
         <tg>
            <t pos="pcle">visst</t>
         </tg>
      </mg>
   </e>
   <e>
      <lg>
         <l pos="pcle">gænnah</l>
      </lg>
      <mg>
         <tg>
            <t pos="pcle">heller</t>
            <t pos="pcle">(ikke) heller</t>
         </tg>
      </mg>
   </e>
   <e>
      <lg>
         <l pos="pcle">hævvi</l>
      </lg>
      <mg>
         <tg>
            <t pos="pcle">selvfølgelig</t>
         </tg>
      </mg>
   </e>
   <e>
      <lg>
         <l pos="pcle">gujht</l>
      </lg>
      <mg>
         <tg>
            <t pos="adv">nok</t>
         </tg>
      </mg>
   </e>
   <e>
      <lg>
         <l pos="pcle">duelie</l>
      </lg>
      <mg>
         <tg>
            <t pos="xxx">vær så god, se der, der (har du)</t>
            <xg>
               <x>Duelie mov tjidtjien tjelmieh.</x>
               <xt>Der ser du min mors øyne.</xt>
               <x>Duelie guessieh båetieh.</x>
               <xt>Se der kommer gjester.</xt>
               <x>Duelie doem.</x>
               <xt>Vær så god og ta denne.</xt>
            </xg>
         </tg>
      </mg>
   </e>
   <e>
      <lg>
         <l pos="pcle">duvlie</l>
      </lg>
      <mg>
         <tg>
            <t pos="xxx">se der</t>
            <xg>
               <x>Duvlie mov tjidtjien tjelmieh.</x>
               <xt>Se der er min mors øyne.</xt>
            </xg>
         </tg>
      </mg>
   </e>
   <e>
      <lg>
         <l pos="pcle">ijje</l>
      </lg>
      <mg>
         <tg>
            <t pos="xxx">nei</t>
         </tg>
      </mg>
   </e>
</r>
