<?xml version="1.0" encoding="UTF-8"?>
<r>
  <e src="nj">
    <lg>
      <l pos="pron" type="dem">dïhte</l>
         <analysis>Pron_Dem_Sg3_Nom</analysis>
         <mini_paradigm>
            <analysis ms="Pron_Dem_Sg3_Acc">
               <wordform>dam gåetiem</wordform>
            </analysis>
            <analysis ms="Pron_Dem_Sg3_Gen">
               <wordform>dan gåetien</wordform>
            </analysis>
            <analysis ms="Pron_Dem_Sg3_Ill">
               <wordform>dan gåatan</wordform>
            </analysis>
            <analysis ms="Pron_Dem_Sg3_Ine">
               <wordform>dennie gåetesne</wordform>
            </analysis>
            <analysis ms="Pron_Dem_Sg3_ELA">
               <wordform>dehtie gåeteste</wordform>
            </analysis>
            <analysis ms="Pron_Dem_Sg3_Com">
               <wordform>dan gåetine</wordform>
            </analysis>            
         </mini_paradigm>
    </lg>
    <mg>
      <tg>
        <t pos="pron">den/det</t>
        <xg>
          <x>Dïhte lea väjkeles gåarodh</x>
          <xt>Han/hun er flink til å sy</xt>
        </xg>
      </tg>
    </mg>
  </e>
  <e src="nj">
    <lg>
      <l pos="pron">daate</l>
         <analysis>Pron_Dem_Sg3_Nom</analysis>
         <mini_paradigm>
            <analysis ms="Pron_Dem_Sg3_Acc">
               <wordform>daam</wordform>
            </analysis>
            <analysis ms="Pron_Dem_Sg3_Gen">
               <wordform>daan</wordform>
            </analysis>
            <analysis ms="Pron_Dem_Sg3_Ill">
               <wordform>daase</wordform>
            </analysis>
            <analysis ms="Pron_Dem_Sg3_Ine">
               <wordform>daesnie</wordform>
            </analysis>
            <analysis ms="Pron_Dem_Sg3_Ela">
               <wordform>daestie</wordform>
            </analysis>
            <analysis ms="Pron_Dem_Sg3_Com">
               <wordform>dáinna</wordform>
            </analysis>
            <analysis ms="Pron_Dem_Sg3_Ess">
               <wordform>daejnie</wordform>
            </analysis>
         </mini_paradigm>
    </lg>
    <mg>
      <tg>
        <t pos="pron">denne/dette (hos meg el. ved meg)</t>
        <xg>
          <x>Daate lea vihkeles aamhtese.</x>
          <xt>Dette er et viktig emne.</xt>
        </xg>
      </tg>
    </mg>
  </e>
    <e src="nj">
    <lg>
      <l pos="pron">doete</l>
         <analysis>Pron_Dem_Sg3_Nom</analysis>
         <mini_paradigm>
            <analysis ms="Pron_Dem_Sg3_Acc">
               <wordform>doem</wordform>
            </analysis>
            <analysis ms="Pron_Dem_Sg3_Gen">
               <wordform>doem</wordform>
            </analysis>
            <analysis ms="Pron_Dem_Sg3_Ill">
               <wordform>doese</wordform>
            </analysis>
            <analysis ms="Pron_Dem_Sg3_Ine">
               <wordform>duesnie</wordform>
            </analysis>
            <analysis ms="Pron_Dem_Sg3_Ela">
               <wordform>duesnie</wordform>
            </analysis>
            <analysis ms="Pron_Dem_Sg3_Com">
               <wordform>duejnie</wordform>
            </analysis>
            <analysis ms="Pron_Dem_Sg3_Ess">
               <wordform>duejnie</wordform>
            </analysis>
         </mini_paradigm>
    </lg>
    <mg>
      <tg>
        <t pos="pron">den/det (den/det der (nærmere deg))</t>
        <xg>
          <x>Mij doete lea?</x>
          <xt>Hva er det (som er der ved deg)?</xt>
        </xg>
      </tg>
    </mg>
  </e>
  <e src="nj">
    <lg>
      <l pos="pron">dohte</l>
         <analysis>Pron_Dem_Sg3_Nom</analysis>
         <mini_paradigm>
            <analysis ms="Pron_Dem_Sg3_Acc">
               <wordform>dom</wordform>
            </analysis>
            <analysis ms="Pron_Dem_Sg3_Gen">
               <wordform>don</wordform>
            </analysis>
            <analysis ms="Pron_Dem_Sg3_Ill">
               <wordform>dosse</wordform>
            </analysis>
            <analysis ms="Pron_Dem_Sg3_Ine">
               <wordform>dusnie</wordform>
            </analysis>
            <analysis ms="Pron_Dem_Sg3_Ela">
               <wordform>dustie</wordform>
            </analysis>
            <analysis ms="Pron_Dem_Sg3_Com">
               <wordform>dujnie</wordform>
            </analysis>
         </mini_paradigm>
    </lg>
    <mg>
      <tg>
        <t pos="pron">den/det det borte (fjernere)</t>
        <xg>
          <x>Gien skuvtere dohte?</x>
          <xt>Hvem sin skoter er det (der borte)?</xt>
        </xg>
      </tg>
    </mg>
  </e>
  <e src="nj">
    <lg>
      <l pos="pron" type="dem">dïhte</l>
         <analysis>Pron_Dem_Pl3_Nom</analysis>
         <mini_paradigm>
            <analysis ms="Pron_Dem_Pl3_Acc">
               <wordform>dejtie gåetide</wordform>
            </analysis>
            <analysis ms="Pron_Dem_Pl3_Gen">
               <wordform>dej gåetiej</wordform>
            </analysis>
            <analysis ms="Pron_Dem_Pl3_Ill">
               <wordform>dejtie gåetide</wordform>
            </analysis>
            <analysis ms="Pron_Dem_Pl3_Ine">
               <wordform>dejnie gåetine</wordform>
            </analysis>
            <analysis ms="Pron_Dem_Pl3_Ela">
               <wordform>dejstie gåetijste</wordform>
            </analysis>
            <analysis ms="Pron_Dem_Pl3_Com">
               <wordform>dej gåetiejgujmie</wordform>
            </analysis>
         </mini_paradigm>
    </lg>
    <mg>
      <tg>
        <t pos="pron">de</t>
        <xg>
          <x></x>
          <xt></xt>
        </xg>
      </tg>
    </mg>
  </e>
  <e src="nj">
    <lg>
      <l pos="pron">daate</l>
         <analysis>Pron_Dem_Pl3_Nom</analysis>
         <mini_paradigm>
            <analysis ms="Pron_Dem_Pl3_Acc">
               <wordform>daejtie</wordform>
            </analysis>
            <analysis ms="Pron_Dem_Pl3_Gen">
               <wordform>daaj</wordform>
            </analysis>
            <analysis ms="Pron_Dem_Pl3_Ill">
               <wordform>daejtie</wordform>
            </analysis>
            <analysis ms="Pron_Dem_Pl3_Ine">
               <wordform>daejnie</wordform>
            </analysis>
            <analysis ms="Pron_Dem_Pl3_Ela">
               <wordform>daejstie</wordform>
            </analysis>
            <analysis ms="Pron_Dem_Pl3_Com">
               <wordform>daejgujmie</wordform>
            </analysis>
         </mini_paradigm>
    </lg>
    <mg>
      <tg>
        <t pos="pron">disse</t>
        <xg>
          <x></x>
          <xt></xt>
        </xg>
      </tg>
    </mg>
  </e>
  <e src="nj">
    <lg>
      <l pos="pron">doehte</l>
         <analysis>Pron_Dem_Pl3_Nom</analysis>
         <mini_paradigm>
            <analysis ms="Pron_Dem_Pl3_Acc">
               <wordform>duetnie</wordform>
            </analysis>
            <analysis ms="Pron_Dem_Pl3_Gen">
               <wordform>doej</wordform>
            </analysis>
            <analysis ms="Pron_Dem_Pl3_Ill">
               <wordform>duejtie</wordform>
            </analysis>
            <analysis ms="Pron_Dem_Pl3_Ine">
               <wordform>duejnie</wordform>
            </analysis>
            <analysis ms="Pron_Dem_Pl3_Ela">
               <wordform>duejstie</wordform>
            </analysis>
            <analysis ms="Pron_Dem_Pl3_Com">
               <wordform>duejgujmie</wordform>
            </analysis>
                     </mini_paradigm>
    </lg>
    <mg>
      <tg>
        <t pos="pron">de (nær deg)</t>
        <xg>
          <x>Doete lea stoere kåahpe.</x>
          <xt>Det der der ei stor kopp (nærmare deg).</xt>
        </xg>
      </tg>
    </mg>
  </e>
  <e src="nj">
    <lg>
      <l pos="pron">dohte</l>
         <analysis>Pron_Dem_Pl3_Nom</analysis>
         <mini_paradigm>
            <analysis ms="Pron_Dem_Pl3_Acc">
               <wordform>dujtie</wordform>
            </analysis>
            <analysis ms="Pron_Dem_Pl3_Gen">
               <wordform>doj, dyj</wordform>
            </analysis>
            <analysis ms="Pron_Dem_Pl3_Ill">
               <wordform>dujtie</wordform>
            </analysis>
            <analysis ms="Pron_Dem_Pl3_Ine">
               <wordform>dujnie</wordform>
            </analysis>
            <analysis ms="Pron_Dem_Pl3_Ela">
               <wordform>dujstie</wordform>
            </analysis>
            <analysis ms="Pron_Dem_Pl3_Com">
               <wordform>dojgujmie</wordform>
            </analysis>
                     </mini_paradigm>
    </lg>
    <mg>
      <tg>
        <t pos="pron">de (der borte)</t>
        <xg>
          <x></x>
          <xt></xt>
        </xg>
      </tg>
    </mg>
  </e>
<!-- example for flected forms -->
   <e>
      <lg>
         <l pos="pron">dan</l>
         <lemma_ref>dat</lemma_ref>
         <analysis>Pron_Dem_Sg3_Gen</analysis>
      </lg>
      <mg>
         <tg>
            <t pos="pron">den/det</t>
        <xg>
          <x>Dan mietie tjoerebe saerniestidh ahte mijjieh dam cookiesem nuhtjebe.</x>
          <xt>I samband med det måste vi också berätta att vi använder den cookien.</xt>
        </xg>
         </tg>
      </mg>
   </e>
   <e>
      <lg>
         <l pos="pron">dejnie</l>
         <lemma_ref>dat</lemma_ref>
         <analysis>Pron_Dem_Sg3_Com</analysis>
      </lg>
      <mg>
         <tg>
            <t pos="pron">med den/det</t>
        <xg>
          <x>Saemiedigkie jih doh aktuelle tjielth edtjieh dejnie barkojne meatan årrodh.</x>
          <xt>Sametinget og de aktuelle kommunene skal være med i det arbeidet.</xt>
        </xg>
         </tg>
      </mg>
   </e>
     <e>
      <lg>
         <l pos="pron">daan</l>
         <lemma_ref>daate</lemma_ref>
         <analysis>Pron_Dem_Sg3_Gen</analysis>
      </lg>
      <mg>
         <tg>
            <t pos="pron">denne/dette</t>
        <xg>
          <x>Jïh båatsoe lea dan dïehre skearkagamme edtja daan kultuvren åejvieguedtije årrodh.</x>
          <xt>Og reindrifta har for den grunn utviklet seg til at bli hovedbærer av denne kulturen.</xt>
        </xg>
         </tg>
      </mg>
   </e>
   <e>
      <lg>
         <l pos="pron">daase</l>
         <lemma_ref>daate</lemma_ref>
         <analysis>Pron_Dem_Sg3_Ill</analysis>
      </lg>
      <mg>
         <tg>
            <t pos="pron">til denne/dette</t>
        <xg>
          <x>Mejtie daerpies daan jijnjh beetnegh daase nuhtjedh?</x>
          <xt>Er det nødvendig å bruke så mye penger til dette?</xt>
        </xg>
         </tg>
      </mg>
   </e>
   <e>
      <lg>
         <l pos="pron">daesnie</l>
         <lemma_ref>daate</lemma_ref>
         <analysis>Pron_Dem_Sg3_Ine</analysis>
      </lg>
      <mg>
         <tg>
            <t pos="pron">i denne/dette</t>
        <xg>
          <x>Daesnie galka åadtjodh daejredh saemien gïelen dovletjen, hammoen jïh struktuvren bïjre.</x>
          <xt>Her skal man få vite om den gammel samisk sin form og strukture.</xt>
        </xg>
         </tg>
      </mg>
   </e>
   <e>
      <lg>
         <l pos="pron">daate</l>
         <lemma_ref>daestie</lemma_ref>
         <analysis>Pron_Dem_Sg3_Ela</analysis>
      </lg>
      <mg>
         <tg>
            <t pos="pron">fra denne/dette</t>
        <xg>
          <x> Daestie maahtah Adobe Acrobat Reader`m vaeltedh.</x>
          <xt>Herifra kan du hente Adobe Acrobat Reader.</xt>
        </xg>
         </tg>
      </mg>
   </e>
   <e>
      <lg>
         <l pos="pron">daejnie</l>
         <lemma_ref>daate</lemma_ref>
         <analysis>Pron_Dem_Sg3_Com</analysis>
      </lg>
      <mg>
         <tg>
            <t pos="pron">med denne/dette</t>
        <xg>
          <x>Guktie maehtebe daejnie darjodh?</x>
          <xt>Hvordan skal vi gøre med dette?</xt>
        </xg>
        </tg>
      </mg>
   </e>
   
      <e>
      <lg>
         <l pos="pron">doehte</l>
         <lemma_ref>duot</lemma_ref>
         <analysis>Pron_Dem_Sg3_Gen</analysis>
         <analysis>Pron_Dem_Sg3_Acc</analysis>
      </lg>
      <mg>
         <tg>
            <t pos="pron">den/det der (som er nærmere deg enn meg)</t>
        <xg>
          <x></x>
          <xt></xt>
        </xg>
         </tg>
      </mg>
   </e>
   <e>
      <lg>
         <l pos="pron">doese</l>
         <lemma_ref>duot</lemma_ref>
         <analysis>Pron_Dem_Sg3_Ill</analysis>
      </lg>
      <mg>
         <tg>
            <t pos="pron">til den/det (som er der borte)</t>
        <xg>
          <x></x>
          <xt></xt>
        </xg>
         </tg>
      </mg>
   </e>
   <e>
      <lg>
         <l pos="pron">duejnie</l>
         <lemma_ref>doehte</lemma_ref>
         <analysis>Pron_Dem_Sg3_Ine</analysis>
      </lg>
      <mg>
         <tg>
            <t pos="pron">i den/det der (som er nærmere deg enn meg)</t>
        <xg>
          <x></x>
          <xt></xt>
        </xg>
         </tg>
      </mg>
   </e>
   <e>
      <lg>
         <l pos="pron">duestie</l>
         <lemma_ref>doehte</lemma_ref>
         <analysis>Pron_Dem_Sg3_Ela</analysis>
      </lg>
      <mg>
         <tg>
            <t pos="pron">fra den/det det (som er nærmere deg enn meg)</t>
        <xg>
          <x></x>
          <xt></xt>
        </xg>
         </tg>
      </mg>
   </e>
   <e>
      <lg>
         <l pos="pron">duejnie</l>
         <lemma_ref>doehte</lemma_ref>
         <analysis>Pron_Dem_Sg3_Com</analysis>
      </lg>
      <mg>
         <tg>
            <t pos="pron">med den/det (som er der borte)</t>
        <xg>
          <x></x>
          <xt></xt>
        </xg>
        </tg>
      </mg>
   </e>
      <e>
      <lg>
         <l pos="pron">dusnie</l>
         <lemma_ref>dohte</lemma_ref>
         <analysis>Pron_Dem_Sg3_Ine</analysis>
      </lg>
      <mg>
         <tg>
            <t pos="pron">i den/det (der borte)</t>
        <xg>
          <x></x>
          <xt></xt>
        </xg>
         </tg>
      </mg>
   </e>
   <e>
      <lg>
         <l pos="pron">dustie</l>
         <lemma_ref>dohte</lemma_ref>
         <analysis>Pron_Dem_Sg3_Ela</analysis>
      </lg>
      <mg>
         <tg>
            <t pos="pron">fra den/det (der borte)</t>
        <xg>
          <x></x>
          <xt></xt>
        </xg>
         </tg>
      </mg>
   </e>
   <e>
      <lg>
         <l pos="pron">dujnie</l>
         <lemma_ref>dohte</lemma_ref>
         <analysis>Pron_Dem_Sg3_Com</analysis>
      </lg>
      <mg>
         <tg>
            <t pos="pron">med den/det (der borte)</t>
        </tg>
      </mg>
   </e>
   <e>
      <lg>
         <l pos="pron">dej</l>
         <lemma_ref>dïhte</lemma_ref>
         <analysis>Pron_Dem_Pl3_Gen</analysis>
      </lg>
      <mg>
         <tg>
            <t pos="pron">deres</t>
        <xg>
          <x></x>
          <xt></xt>
        </xg>
         </tg>
      </mg>
   </e>
   <e>
      <lg>
         <l pos="pron">daidda</l>
         <lemma_ref>dat</lemma_ref>
         <analysis>Pron_Dem_Pl3_Ill</analysis>
      </lg>
      <mg>
         <tg>
            <t pos="pron">til dem</t>
        <xg>
          <x>Daate lij dej jaepien vihkelommes heevehtimmie, jih giesiem heevehtin.</x>
          <xt>Dette var deres viktigeste høytid, da de fierte sommeren.</xt>
        </xg>
         </tg>
      </mg>
   </e>
   <e>
      <lg>
         <l pos="pron">dejnie</l>
         <lemma_ref>dïhte</lemma_ref>
         <analysis>Pron_Dem_Pl3_Ine</analysis>
      </lg>
      <mg>
         <tg>
            <t pos="pron">i dem</t>
        <xg>
          <x>Vuajnah doh gåetieh? Dejnie manne gellie jïjjh höölestamme.</x>
          <xt>Ser du de husene? I dem har jeg bodd mange netter.</xt>
        </xg>
         </tg>
      </mg>
   </e>
   <e>
      <lg>
         <l pos="pron">dejstie</l>
         <lemma_ref>dat</lemma_ref>
         <analysis>Pron_Dem_Pl3_Ela</analysis>
      </lg>
      <mg>
         <tg>
            <t pos="pron">i dem</t>
        <xg>
          <x>Dat lea okta dain sámi viesuin mat galget huksejuvvot riikkas.</x>
          <xt>Det er ett av de samiske husene som skal bygges i landet.</xt>
        </xg>
         </tg>
      </mg>
   </e>
   <e>
      <lg>
         <l pos="pron">daiguin</l>
         <lemma_ref>dat</lemma_ref>
         <analysis>Pron_Dem_Pl3_Com</analysis>
      </lg>
      <mg>
         <tg>
            <t pos="pron">med dem</t>
        <xg>
          <x>Daiguin áššiiguin manná hui bures.</x>
          <xt>Med de sakene går det veldig bra.</xt>
        </xg>
         </tg>
      </mg>
   </e>
   <e>
      <lg>
         <l pos="pron">danin</l>
         <lemma_ref>dat</lemma_ref>
         <analysis>Pron_Dem_Pl3_Ess</analysis>
      </lg>
      <mg>
         <tg>
            <t pos="pron">som det</t>
            <t pos="pron">som den</t>
        <xg>
          <x></x>
          <xt></xt>
        </xg>
         </tg>
      </mg>
   </e>

   <e>
      <lg>
         <l pos="pron">dáid</l>
         <lemma_ref>dát</lemma_ref>
         <analysis>Pron_Dem_Pl3_Gen</analysis>
         <analysis>Pron_Dem_Pl3_Acc</analysis>
      </lg>
      <mg>
         <tg>
            <t pos="pron">disse</t>
            <t pos="pron">disse "sin"</t>
        <xg>
          <x>Ii leat midjiide jienádan goassige ovdal dáid jurdagiid.</x>
          <xt>Han/hun har ikke noen gang nevnt disse tankene til oss.</xt>
        </xg>
         </tg>
      </mg>
   </e>
   <e>
      <lg>
         <l pos="pron">dáidda</l>
         <lemma_ref>dát</lemma_ref>
         <analysis>Pron_Dem_Pl3_Ill</analysis>
      </lg>
      <mg>
         <tg>
            <t pos="pron">til disse</t>
        <xg>
          <x></x>
          <xt></xt>
        </xg>
         </tg>
      </mg>
   </e>
   <e>
      <lg>
         <l pos="pron">daejnie</l>
         <lemma_ref>daate</lemma_ref>
         <analysis>Pron_Dem_Pl3_Ine</analysis>
      </lg>
      <mg>
         <tg>
            <t pos="pron">i dette</t>
            <t pos="pron">i denne</t>
        <xg>
          <x></x>
          <xt></xt>
        </xg>
         </tg>
      </mg>
   </e>
   <e>
      <lg>
         <l pos="pron">daejstie</l>
         <lemma_ref>daate</lemma_ref>
         <analysis>Pron_Dem_Pl3_Ela</analysis>
      </lg>
      <mg>
         <tg>
            <t pos="pron">i dette</t>
            <t pos="pron">i denne</t>
        <xg>
          <x></x>
          <xt></xt>
        </xg>
         </tg>
      </mg>
   </e>
   <e>
      <lg>
         <l pos="pron">daajgujmie</l>
         <lemma_ref>daate</lemma_ref>
         <analysis>Pron_Dem_Pl3_Com</analysis>
      </lg>
      <mg>
         <tg>
            <t pos="pron">med disse</t>
        <xg>
          <x>Dïhte jïjnje daajgujmie barkeme.</x>
          <xt>Han/hur har arbeidet mye med disse.</xt>
        </xg>
        </tg>
      </mg>
   </e>
     <e>
      <lg>
         <l pos="pron">duej</l>
         <lemma_ref>duot</lemma_ref>
         <analysis>Pron_Dem_Pl3_Gen</analysis>
      </lg>
      <mg>
         <tg>
            <t pos="pron">de der sin (som er nærmere deg enn meg)</t>
        <xg>
          <x></x>
          <xt></xt>
        </xg>
         </tg>
      </mg>
   </e>
   <e>
      <lg>
         <l pos="pron">duejtie</l>
         <lemma_ref>doehte</lemma_ref>
         <analysis>Pron_Dem_Pl3_Ill</analysis>
      </lg>
      <mg>
         <tg>
            <t pos="pron">til dem (som er nærmere deg enn meg)</t>
        <xg>
          <x></x>
          <xt> </xt>
        </xg>
         </tg>
      </mg>
   </e>
   <e>
      <lg>
         <l pos="pron">duejnie</l>
         <lemma_ref>doehte</lemma_ref>
         <analysis>Pron_Dem_Pl3_Ine</analysis>
      </lg>
      <mg>
         <tg>
            <t pos="pron">i dem (som er nærmere deg enn meg)</t>
        <xg>
          <x></x>
          <xt></xt>
        </xg>
         </tg>
      </mg>
   </e>
   <e>
      <lg>
         <l pos="pron">duejstie</l>
         <lemma_ref>doehte</lemma_ref>
         <analysis>Pron_Dem_Pl3_Ela</analysis>
      </lg>
      <mg>
         <tg>
            <t pos="pron">i dem (som er nærmere deg enn meg)</t>
        <xg>
          <x></x>
          <xt></xt>
        </xg>
         </tg>
      </mg>
   </e>
   <e>
      <lg>
         <l pos="pron">duejgujmie</l>
         <lemma_ref>duot</lemma_ref>
         <analysis>Pron_Dem_Pl3_Com</analysis>
      </lg>
      <mg>
         <tg>
            <t pos="pron">med dem (som er nærmere deg enn meg)</t>
        <xg>
          <x></x>
          <xt></xt>
        </xg>
        </tg>
      </mg>
   </e>
      <e>
      <lg>
         <l pos="pron">doj</l>
         <lemma_ref>dohte</lemma_ref>
         <analysis>Pron_Dem_Pl3_Gen</analysis>
      </lg>
      <mg>
         <tg>
            <t pos="pron">deres (der borte)</t>
        <xg>
          <x></x>
          <xt></xt>
        </xg>
         </tg>
      </mg>
   </e>
   <e>
      <lg>
         <l pos="pron">dujtie</l>
         <lemma_ref>dohte</lemma_ref>
         <analysis>Pron_Dem_Pl3_Ill</analysis>
      </lg>
      <mg>
         <tg>
            <t pos="pron">til dem (der borte)</t>
        <xg>
          <x></x>
          <xt></xt>
        </xg>
         </tg>
      </mg>
   </e>
   <e>
      <lg>
         <l pos="pron">dujnie</l>
         <lemma_ref>dohte</lemma_ref>
         <analysis>Pron_Dem_Pl3_Ine</analysis>
      </lg>
      <mg>
         <tg>
            <t pos="pron">i dem (der borte)</t>
        <xg>
          <x></x>
          <xt></xt>
        </xg>
         </tg>
      </mg>
   </e>
   <e>
      <lg>
         <l pos="pron">dujstie</l>
         <lemma_ref>dohte</lemma_ref>
         <analysis>Pron_Dem_Pl3_Ela</analysis>
      </lg>
      <mg>
         <tg>
            <t pos="pron">i dem (der borte)</t>
        <xg>
          <x></x>
          <xt></xt>
        </xg>
         </tg>
      </mg>
   </e>
   <e>
      <lg>
         <l pos="pron">dojgujmie</l>
         <lemma_ref>dohte</lemma_ref>
         <analysis>Pron_Dem_Pl3_Com</analysis>
      </lg>
      <mg>
         <tg>
            <t pos="pron">med dem (der borte)</t>
        </tg>
      </mg>
   </e>
  </r>
